drf_groups/__init__.py
drf_groups/permissions.py
drf_groups-0.2.0.dist-info/WHEEL
drf_groups-0.2.0.dist-info/METADATA
drf_groups-0.2.0.dist-info/RECORD
