Metadata-Version: 2.1
Name: drf-groups
Version: 0.2.0
Summary: 
License: MIT
Author: Paris Kasidiaris
Author-email: paris@sourcelair.com
Requires-Python: >=3.8,<4.0
Classifier: License :: OSI Approved :: MIT License
Classifier: Programming Language :: Python :: 3
Classifier: Programming Language :: Python :: 3.8
Classifier: Programming Language :: Python :: 3.9
Requires-Dist: djangorestframework (>=3.11.0)
